<?xml version="1.0" encoding="utf-8" ?>
<dwsync>
<file name="jquery.min.js" server="C:/xamppp/htdocs/medical" local="130643705760000000" remote="130643705760000000" Dst="0" />
<file name="bootstrap-3.1.1.min.js" server="C:/xamppp/htdocs/medical" local="130843867900000000" remote="130843867900000000" Dst="0" />
<file name="simpleCart.min.js" server="C:/xamppp/htdocs/medical" local="130843890360000000" remote="130843890360000000" Dst="0" />
<file name="responsiveslides.min.js" server="C:/xamppp/htdocs/medical" local="130844493560000000" remote="130844493560000000" Dst="0" />
<file name="jquery.flexisel.js" server="C:/xamppp/htdocs/medical" local="130844619020000000" remote="130844619020000000" Dst="0" />
<file name="jquery.min.js" server="C:/xamppp/htdocs/medical/" local="130643705760000000" remote="130643705760000000" Dst="0" />
<file name="bootstrap-3.1.1.min.js" server="C:/xamppp/htdocs/medical/" local="130843867900000000" remote="130843867900000000" Dst="0" />
<file name="simpleCart.min.js" server="C:/xamppp/htdocs/medical/" local="130843890360000000" remote="130843890360000000" Dst="0" />
<file name="responsiveslides.min.js" server="C:/xamppp/htdocs/medical/" local="130844493560000000" remote="130844493560000000" Dst="0" />
<file name="jquery.flexisel.js" server="C:/xamppp/htdocs/medical/" local="130844619020000000" remote="130844619020000000" Dst="0" />
</dwsync>